mtdynamics/__init__.py
mtdynamics/plotting_functions.py
mtdynamics/simulation_functions.py
mtdynamics/simulation_main.py
mtdynamics/simulation_parameters.py
mtdynamics/simulation_screening.py
mtdynamics-0.1.1.dist-info/LICENSE
mtdynamics-0.1.1.dist-info/METADATA
mtdynamics-0.1.1.dist-info/WHEEL
mtdynamics-0.1.1.dist-info/top_level.txt
mtdynamics-0.1.1.dist-info/RECORD
