Metadata-Version: 2.1
Name: mtdynamics
Version: 0.1.1
Summary: MT dynamics simulation
Home-page: https://github.com/florian-huber/mt-dynamics
Author: Florian Huber and Maurits Kok
Author-email: f.huber@esciencecenter.nl
License: UNKNOWN
Platform: UNKNOWN
Classifier: Programming Language :: Python :: 3
Classifier: License :: OSI Approved :: Apache Software License
Classifier: Operating System :: OS Independent
Requires-Python: >=3.6
Requires-Dist: matplotlib
Requires-Dist: numpy
Requires-Dist: pandas
Requires-Dist: parameters
Requires-Dist: scipy
